tomodachi/__init__.py
tomodachi/__init__.pyi
tomodachi/__main__.py
tomodachi/__version__.py
tomodachi/_exception.py
tomodachi/_importer.py
tomodachi/cli/__init__.py
tomodachi/config.py
tomodachi/container.py
tomodachi/discovery/__init__.py
tomodachi/discovery/__init__.pyi
tomodachi/discovery/aws_sns_registration.py
tomodachi/discovery/dummy_registry.py
tomodachi/envelope/__init__.py
tomodachi/envelope/__init__.pyi
tomodachi/envelope/json_base.py
tomodachi/envelope/proto_build/__init__.py
tomodachi/envelope/proto_build/protobuf/__init__.py
tomodachi/envelope/proto_build/protobuf/sns_sqs_message_pb2.py
tomodachi/envelope/proto_build/protobuf/sns_sqs_message_pb2.pyi
tomodachi/envelope/protobuf/sns_sqs_message.proto
tomodachi/envelope/protobuf_base.py
tomodachi/helpers/__init__.py
tomodachi/helpers/aiobotocore_connector.py
tomodachi/helpers/aws_credentials.py
tomodachi/helpers/banner.py
tomodachi/helpers/build_time.py
tomodachi/helpers/colors.py
tomodachi/helpers/crontab.py
tomodachi/helpers/dict.py
tomodachi/helpers/execution_context.py
tomodachi/helpers/logging.py
tomodachi/helpers/middleware.py
tomodachi/helpers/safe_modules.py
tomodachi/importer.py
tomodachi/invoker/__init__.py
tomodachi/invoker/base.py
tomodachi/invoker/decorator.py
tomodachi/launcher.py
tomodachi/logging.py
tomodachi/opentelemetry/__init__.py
tomodachi/opentelemetry/auto_instrumentation.py
tomodachi/opentelemetry/distro.py
tomodachi/opentelemetry/environment_variables.py
tomodachi/opentelemetry/exemplars.py
tomodachi/opentelemetry/instrumentation.py
tomodachi/opentelemetry/logging.py
tomodachi/opentelemetry/middleware.py
tomodachi/opentelemetry/prometheus.py
tomodachi/options/__init__.py
tomodachi/options/definitions.py
tomodachi/options/interface.py
tomodachi/protocol/__init__.py
tomodachi/protocol/__init__.pyi
tomodachi/protocol/json_base.py
tomodachi/protocol/protobuf_base.py
tomodachi/py.typed
tomodachi/run/__main__.py
tomodachi/transport/__init__.py
tomodachi/transport/__init__.pyi
tomodachi-0.28.3.dist-info/LICENSE
tomodachi-0.28.3.dist-info/METADATA
tomodachi-0.28.3.dist-info/WHEEL
tomodachi-0.28.3.dist-info/entry_points.txt
tomodachi-0.28.3.dist-info/RECORD
