Metadata-Version: 2.1
Name: tomodachi
Version: 0.28.3
Summary: Microservice library on asyncio - HTTP server, websockets, pub/sub messaging for AWS SNS+SQS and RabbitMQ
Home-page: https://github.com/kalaspuff/tomodachi
License: MIT
Keywords: tomodachi,microservice,microservices,framework,library,asyncio,aws,sns,sqs,amqp,rabbitmq,http,websockets,easy,fast,pubsub,events,event based messaging,messages,protocol buffers,protobuf,async,message attributes,filter policy,distributed architecture,scalable,python 3
Author: Carl Oscar Aaro
Author-email: hello@carloscar.com
Requires-Python: >=3.9,<4.0
Classifier: Development Status :: 4 - Beta
Classifier: Framework :: AsyncIO
Classifier: Framework :: aiohttp
Classifier: Intended Audience :: Developers
Classifier: Intended Audience :: System Administrators
Classifier: License :: OSI Approved :: MIT License
Classifier: Operating System :: MacOS
Classifier: Operating System :: MacOS :: MacOS X
Classifier: Operating System :: POSIX
Classifier: Operating System :: POSIX :: Linux
Classifier: Programming Language :: Python :: 3
Classifier: Programming Language :: Python :: 3.9
Classifier: Programming Language :: Python :: 3.10
Classifier: Programming Language :: Python :: 3.11
Classifier: Programming Language :: Python :: 3.12
Classifier: Programming Language :: Python :: 3 :: Only
Classifier: Programming Language :: Python :: 3.13
Classifier: Topic :: Software Development :: Libraries :: Application Frameworks
Classifier: Topic :: Software Development :: Libraries :: Python Modules
Classifier: Topic :: System :: Distributed Computing
Classifier: Typing :: Typed
Provides-Extra: aiodns
Provides-Extra: amqp
Provides-Extra: aws
Provides-Extra: brotli
Provides-Extra: color
Provides-Extra: http
Provides-Extra: instruments
Provides-Extra: opentelemetry
Provides-Extra: opentelemetry-exporter-prometheus
Provides-Extra: protobuf
Provides-Extra: scheduler
Provides-Extra: uvloop
Requires-Dist: Brotli (>=1.0.9,<2.0.0) ; extra == "brotli"
Requires-Dist: aioamqp (>=0.13.0,<0.16.0)
Requires-Dist: aiobotocore (>=2.0.0,<3.0.0)
Requires-Dist: aiodns (>=1.2.0) ; extra == "aiodns"
Requires-Dist: aiohttp (>=3.9.5,<3.11.0)
Requires-Dist: asahi (>=0.1,<0.3)
Requires-Dist: asahi-extras ; extra == "aws" or extra == "amqp" or extra == "http" or extra == "scheduler" or extra == "color"
Requires-Dist: botocore (>=1.22.8)
Requires-Dist: cchardet (>=2.1.7) ; python_version < "3.10"
Requires-Dist: colorama (>=0.3.9,<0.5.0)
Requires-Dist: opentelemetry-api (>=1.27.0,<1.28.0) ; extra == "opentelemetry" or extra == "opentelemetry-exporter-prometheus"
Requires-Dist: opentelemetry-exporter-otlp (>=1.27.0,<1.28.0) ; extra == "opentelemetry" or extra == "opentelemetry-exporter-prometheus"
Requires-Dist: opentelemetry-exporter-prometheus (>=0.48b0,<1.0.0) ; extra == "opentelemetry-exporter-prometheus"
Requires-Dist: opentelemetry-instrumentation (>=0.48b0,<1.0.0) ; extra == "opentelemetry" or extra == "opentelemetry-exporter-prometheus"
Requires-Dist: opentelemetry-sdk (>=1.27.0,<1.28.0) ; extra == "opentelemetry" or extra == "opentelemetry-exporter-prometheus"
Requires-Dist: opentelemetry-util-http (>=0.48b0,<1.0.0) ; extra == "opentelemetry" or extra == "opentelemetry-exporter-prometheus"
Requires-Dist: protobuf (>=4.25.0) ; extra == "protobuf"
Requires-Dist: pytz
Requires-Dist: structlog (>=21.5.0,<25.0.0)
Requires-Dist: tzlocal (>=1.4,<6.0)
Requires-Dist: uvloop (>=0.14.0,<1.0.0) ; extra == "uvloop"
Requires-Dist: yarl (>=1.16.0,<2.0.0)
Project-URL: Changelog, https://github.com/kalaspuff/tomodachi/blob/master/CHANGELOG.md
Project-URL: Documentation, https://tomodachi.dev/docs
Project-URL: Repository, https://github.com/kalaspuff/tomodachi
